{"jakarta":1,"mantan":2,"ketua":1,"kpk":1,"antasari":10,"azhar":2,"hirup":1,"udara":1,"bebas":3,"november":1,"wib":2,"saat":1,"jalan":2,"proses":2,"asimilasi":4,"kantor":3,"notaris":4,"tangerang":1,"lp":3,"hun":1,"saya":1,"konsultasi":2,"hukum":6,"bidang":1,"jadi":2,"tenaga":1,"ahli":1,"detikcom":1,"selasa":1,"bagai":1,"narapidana":1,"syarat":1,"hak":3,"adaptasi":1,"dunia":2,"nilai":1,"jaksa":1,"senior":1,"hari":1,"gelut":1,"seperti":1,"bingung":1,"solusi":2,"ubah":1,"waris":3,"hibah":2,"banyak":1,"orang":1,"tua":1,"anak":2,"senang":1,"nomor":1,"tinggal":1,"saudara":1,"tuntut":1,"turut":1,"dara":1,"hilang":2,"gugat":3,"cerita":1,"kerja":1,"konsultan":1,"sentuh":1,"masyarakat":1,"tiap":1,"berangkat":1,"pulang":1,"lepas":1,"siang":1,"paham":1,"mediasi":1,"data":1,"seni":2,"bagaimana":1,"penjara":1,"tingkat":4,"kuat":2,"majelis":1,"banding":2,"kasasi":2,"tinjau":1,"yakin":1,"bunuh":2,"nasrudin":5,"tapi":2,"hakim":5,"agung":3,"putus":1,"murni":1,"libat":1,"prof":1,"dr":1,"surya":1,"jaya":1,"curhat":1,"kasus":1,"sigit":2,"haryo":2,"tetapi":1,"kalimat":1,"suruh":1,"wibisono":1,"habis":1,"nyawa":1,"salah":1,"misteri":1,"mati":1,"baju":2,"pakai":1,"tembak":2,"telah":1,"bawa":1,"rs":2,"mayapada":2,"tangan":1,"terus":1,"rscm":1,"sidang":1,"bukti":1,"asp":2,"":1}